{
  "objectName": "roster",
  "alias": "roster",
  "schemaDescription": "",
  "schemaObject": {
    "name": "roster",
    "columns": {
      "id": {
        "primary": true,
        "autoGenerated": true,
        "minValue": 1,
        "maxValue": 0,
        "prefix": "roster-",
        "unique": true,
        "indexed": true,
        "identifier": true,
        "type": "text"
      },
      "Name": {
        "generated": false,
        "indexed": false,
        "nullable": true,
        "primary": false,
        "required": false,
        "type": "varchar",
        "unique": null
      }
    },
    "relations": {}
  },
  "schemaValidation": {
    "name": "roster",
    "properties": {
      "id": {
        "label": "id",
        "fieldType": "generated-primary",
        "description": "",
        "helpText": ""
      },
      "Name": {
        "fieldType": "long_text",
        "helpText": null,
        "label": "name",
        "private": false,
        "description": null,
        "type": "string",
        "minLength": 1,
        "maxLength": 1000000
      }
    },
    "inverseSideProperties": {}
  },"fieldsToAdd": []
}