{
  "objectName": "season_league",
  "alias": "season_league",
  "schemaDescription": "",
  "schemaObject": {
    "name": "season_league",
    "columns": {
      "season_league": {
        "primary": true,
        "autoGenerated": true,
        "minValue": 1,
        "maxValue": 0,
        "prefix": "season_league-",
        "unique": true,
        "indexed": true,
        "identifier": true,
        "type": "text"
      }
    },
    "relations": {
      "teams": {
        "target": "core-sports-dev_team",
        "type": "one-to-many",
        "joinColumn": { "name": "TeamsId", "referencedColumnName": "id" },
        "onDelete": "SET NULL",
        "cascade": false,
        "nullable": true,
        "inverseSide": "season_league_teams_inverseside"
      },
      "season": {
        "target": "core-sports-dev_season",
        "type": "many-to-one",
        "joinColumn": { "name": "SeasonId", "referencedColumnName": "id" },
        "onDelete": "SET NULL",
        "cascade": false,
        "nullable": true,
        "inverseSide": "season_league_season_inverseside"
      },
      "league": {
        "target": "core-sports-dev_league",
        "type": "many-to-one",
        "joinColumn": { "name": "LeagueId", "referencedColumnName": "id" },
        "onDelete": "SET NULL",
        "cascade": false,
        "nullable": true,
        "inverseSide": "season_league_league_inverseside"
      }
    }
  },
  "schemaValidation": {
    "name": "season_league",
    "properties": {
      "season_league": {
        "label": "season_league",
        "fieldType": "generated-primary",
        "description": "",
        "helpText": ""
      },
      "teams": {
        "relatedFieldLabel": "",
        "relatedFieldHelpText": "",
        "label": "teams",
        "helpText": null,
        "fieldType": "one-to-many",
        "private": null,
        "description": null,
        "required": false,
        "type": "array",
        "items": { "type": "objects" }
      },
      "season": {
        "relatedFieldLabel": "season_league",
        "relatedFieldHelpText": "",
        "label": "Season",
        "helpText": null,
        "fieldType": "many-to-one",
        "private": null,
        "description": null,
        "required": false,
        "type": ["number", "object"]
      },
      "league": {
        "relatedFieldLabel": "season league",
        "relatedFieldHelpText": "",
        "label": "league",
        "helpText": null,
        "fieldType": "many-to-one",
        "private": null,
        "description": null,
        "required": false,
        "type": ["number", "object"]
      }
    },
    "inverseSideProperties": {
      "season_league_teams_inverseside": { "label": "", "helpText": "" },
      "season_league_season_inverseside": {
        "label": "season_league",
        "helpText": ""
      },
      "season_league_league_inverseside": {
        "label": "season league",
        "helpText": ""
      }
    }
  },
  "relationsToAdd": ["teams", "season", "league"]
}